Metadata-Version: 2.1
Name: hanane-linear-regression
Version: 1.0.0
Summary: An awesome package that implements a Simple Linear Regression Model.
Home-page: http://pypi.python.org/pypi/hanane_linear_regression/
Author: Hanane SABOUNI
Author-email: h.sabouni@esi-sba.dz
License: LICENSE.txt
License-File: LICENCE.TXT
